tianxiadatong_qq_robot/__init__.cp312-win_amd64.pyd
tianxiadatong_qq_robot/__init__.py
tianxiadatong_qq_robot/handler.cp312-win_amd64.pyd
tianxiadatong_qq_robot/local_logger.cp312-win_amd64.pyd
tianxiadatong_qq_robot/main.cp312-win_amd64.pyd
tianxiadatong_qq_robot/message.cp312-win_amd64.pyd
tianxiadatong_qq_robot/processor.cp312-win_amd64.pyd
tianxiadatong_qq_robot/public.cp312-win_amd64.pyd
tianxiadatong_qq_robot/qqApp.cp312-win_amd64.pyd
tianxiadatong_qq_robot-0.1.9.dist-info/METADATA
tianxiadatong_qq_robot-0.1.9.dist-info/WHEEL
tianxiadatong_qq_robot-0.1.9.dist-info/top_level.txt
tianxiadatong_qq_robot-0.1.9.dist-info/RECORD
