Metadata-Version: 2.4
Name: tianxiadatong_qq_robot
Version: 0.1.9
Summary: tianxiadatong_qq_robot SDK
Requires-Python: >=3.8
Requires-Dist: sentry-sdk==0.10.2
Requires-Dist: websockets==15.0.1
Requires-Dist: aiohttp==3.12.15
Requires-Dist: cryptography==46.0.1
Requires-Dist: uvicorn==0.35.0
Requires-Dist: requests==2.32.5
Requires-Dist: psutil==7.1.0
Requires-Dist: APScheduler==3.11.0
Requires-Dist: pydantic==2.11.9
Requires-Dist: esdk-obs-python==3.25.3
Requires-Dist: fastapi==0.116.2
Requires-Dist: aiofiles==24.1.0
